odoo/addons/sequence_range_end/README.rst
odoo/addons/sequence_range_end/__init__.py
odoo/addons/sequence_range_end/__manifest__.py
odoo/addons/sequence_range_end/i18n/sequence_range_end.pot
odoo/addons/sequence_range_end/models/__init__.py
odoo/addons/sequence_range_end/models/ir_sequence.py
odoo/addons/sequence_range_end/readme/CONTRIBUTORS.rst
odoo/addons/sequence_range_end/readme/DESCRIPTION.rst
odoo/addons/sequence_range_end/static/description/icon.png
odoo/addons/sequence_range_end/static/description/index.html
odoo/addons/sequence_range_end/tests/__init__.py
odoo/addons/sequence_range_end/tests/test_sequence_range_end.py
odoo/addons/sequence_range_end/views/sequence_views.xml
odoo14_addon_sequence_range_end-14.0.1.0.1.dist-info/METADATA
odoo14_addon_sequence_range_end-14.0.1.0.1.dist-info/WHEEL
odoo14_addon_sequence_range_end-14.0.1.0.1.dist-info/top_level.txt
odoo14_addon_sequence_range_end-14.0.1.0.1.dist-info/RECORD
